pdal_ign_macro/__init__.py
pdal_ign_macro/macro.py
pdal_ign_macro/main_preprocessing_mnx.py
pdal_ign_macro/mark_points_to_use_for_digital_models_with_new_dimension.py
pdal_ign_macro/reassign_classification_for_digital_model.py
pdal_ign_macro/version.py
pdal_ign_macro-0.6.0.dist-info/METADATA
pdal_ign_macro-0.6.0.dist-info/WHEEL
pdal_ign_macro-0.6.0.dist-info/top_level.txt
pdal_ign_macro-0.6.0.dist-info/RECORD
