Metadata-Version: 2.4
Name: pdal_ign_macro
Version: 0.6.0
Summary: Macros and pipelines for Pdal based on the https://github.com/IGNF/pdal-ign-plugin plugin
Author-email: Antoine Lavenant <antoine.lavenant@ign.fr>, Léa Vauchier <lea.vauchier@ign.fr>
